viasp_dash/__init__.py
viasp_dash/_imports_.py
viasp_dash/async-IconWrapper.js
viasp_dash/async-IconWrapper.js.map
viasp_dash/async-Settings.js
viasp_dash/async-Settings.js.map
viasp_dash/colorPalette.json
viasp_dash/config.json
viasp_dash/f4aa8d5277a7f7647833.png
viasp_dash/favicon.ico
viasp_dash/index.html
viasp_dash/metadata.json
viasp_dash/package-info.json
viasp_dash/react_server.py
viasp_dash/viasp_dash.min.js
viasp_dash/viasp_dash.min.js.map
viasp_dash-2.3.0.post3.dist-info/licenses/LICENCE.md
viasp_dash-2.3.0.post3.dist-info/METADATA
viasp_dash-2.3.0.post3.dist-info/WHEEL
viasp_dash-2.3.0.post3.dist-info/entry_points.txt
viasp_dash-2.3.0.post3.dist-info/top_level.txt
viasp_dash-2.3.0.post3.dist-info/RECORD
