Metadata-Version: 2.4
Name: viasp_dash
Version: 2.3.0.post3
Summary: The dash frontend for the viasp package.
Author: Luis Glaser <Luis.Glaser@uni-potsdam.de>
License: MIT
Classifier: Framework :: Flask
Classifier: Programming Language :: JavaScript
Classifier: Programming Language :: Python
License-File: LICENCE.md
Dynamic: author
Dynamic: classifier
Dynamic: description
Dynamic: description-content-type
Dynamic: license
Dynamic: license-file
Dynamic: summary
